partcl/__init__.py
partcl/_version.py
partcl/api.py
partcl/main.py
partcl/client/__init__.py
partcl/client/api.py
partcl/client/storage.py
partcl/commands/__init__.py
partcl/commands/auth.py
partcl/commands/timing.py
partcl/utils/__init__.py
partcl/utils/config.py
partcl/utils/validation.py
partcl_cli-0.1.0.dist-info/licenses/LICENSE
partcl_cli-0.1.0.dist-info/METADATA
partcl_cli-0.1.0.dist-info/WHEEL
partcl_cli-0.1.0.dist-info/entry_points.txt
partcl_cli-0.1.0.dist-info/top_level.txt
partcl_cli-0.1.0.dist-info/RECORD
